odoo/addons/sale_lead_time_range/README.rst
odoo/addons/sale_lead_time_range/__init__.py
odoo/addons/sale_lead_time_range/__manifest__.py
odoo/addons/sale_lead_time_range/init_hook.py
odoo/addons/sale_lead_time_range/i18n/sale_lead_time_range.pot
odoo/addons/sale_lead_time_range/models/__init__.py
odoo/addons/sale_lead_time_range/models/product.py
odoo/addons/sale_lead_time_range/models/sale_order_line.py
odoo/addons/sale_lead_time_range/readme/CONTRIBUTORS.rst
odoo/addons/sale_lead_time_range/readme/DESCRIPTION.rst
odoo/addons/sale_lead_time_range/readme/USAGE.rst
odoo/addons/sale_lead_time_range/static/description/icon.png
odoo/addons/sale_lead_time_range/static/description/index.html
odoo/addons/sale_lead_time_range/tests/__init__.py
odoo/addons/sale_lead_time_range/tests/test_sale_lead_time_range.py
odoo/addons/sale_lead_time_range/views/product_views.xml
odoo/addons/sale_lead_time_range/views/sale_order_line.xml
odoo_addon_sale_lead_time_range-15.0.1.0.0.2.dist-info/METADATA
odoo_addon_sale_lead_time_range-15.0.1.0.0.2.dist-info/WHEEL
odoo_addon_sale_lead_time_range-15.0.1.0.0.2.dist-info/top_level.txt
odoo_addon_sale_lead_time_range-15.0.1.0.0.2.dist-info/RECORD
